tlearner/__init__.py
tlearner/efficientnet.py
tlearner/mask_fundus.bmp
tlearner-0.1.5.dist-info/METADATA
tlearner-0.1.5.dist-info/WHEEL
tlearner-0.1.5.dist-info/top_level.txt
tlearner-0.1.5.dist-info/RECORD
