Metadata-Version: 2.1
Name: tlearner
Version: 0.1.5
Summary: A python library for neural network transfer learning.
Home-page: https://github.com/zhangys11/tlearner
Author: Yinsheng Zhang (Ph.D.)
Author-email: oo@zju.edu.cn
Project-URL: Bug Tracker, https://github.com/zhangys11/tlearner/issues
Classifier: Programming Language :: Python :: 3
Classifier: License :: OSI Approved :: GNU Lesser General Public License v3 or later (LGPLv3+)
Classifier: Operating System :: OS Independent
Classifier: Topic :: Scientific/Engineering :: Mathematics
Requires-Python: >=3.6
Requires-Dist: scikit-learn
Requires-Dist: scipy
Requires-Dist: uuid
Requires-Dist: pandas
Requires-Dist: matplotlib
Requires-Dist: numpy
Requires-Dist: seaborn
Requires-Dist: keras
